[{"word": "Takkie", "position": [165, 178, 218, 47]}, {"word": "is", "position": [408, 178, 51, 46]}, {"word": "een", "position": [484, 191, 111, 34]}, {"word": "lief", "position": [618, 178, 106, 47]}, {"word": "hondje", "position": [742, 178, 219, 60]}, {"word": "\u2018Takkie,\u2019", "position": [165, 381, 121, 25]}, {"word": "zegt", "position": [298, 382, 62, 27]}, {"word": "Jip.", "position": [371, 381, 51, 28]}, {"word": "\u201cVan", "position": [436, 381, 61, 21]}, {"word": "wie", "position": [508, 381, 50, 21]}, {"word": "hou", "position": [569, 381, 56, 21]}, {"word": "je", "position": [633, 381, 27, 28]}, {"word": "meer,", "position": [671, 387, 78, 19]}, {"word": "van", "position": [163, 431, 54, 16]}, {"word": "mij", "position": [228, 426, 44, 27]}, {"word": "of", "position": [285, 425, 30, 22]}, {"word": "van", "position": [322, 431, 53, 16]}, {"word": "Janneke?", "position": [386, 425, 139, 22]}, {"word": "Zeg", "position": [535, 426, 55, 27]}, {"word": "het", "position": [600, 426, 46, 21]}, {"word": "eens,", "position": [657, 431, 74, 20]}, {"word": "Takkie.\u2019", "position": [164, 470, 116, 22]}, {"word": "\u2018Waf,", "position": [165, 515, 75, 25]}, {"word": "zegt", "position": [251, 516, 62, 27]}, {"word": "Takkie.", "position": [324, 515, 107, 21]}, {"word": "\u2018Hou", "position": [165, 559, 67, 22]}, {"word": "je", "position": [240, 560, 28, 27]}, {"word": "meer", "position": [279, 565, 74, 16]}, {"word": "van", "position": [363, 565, 53, 16]}, {"word": "mij?\u2019", "position": [427, 559, 68, 28]}, {"word": "vraagt", "position": [506, 560, 97, 27]}, {"word": "Janneke.", "position": [614, 560, 131, 21]}, {"word": "\u2018Waf,", "position": [165, 604, 75, 26]}, {"word": "zegt", "position": [251, 605, 62, 27]}, {"word": "Takkie.", "position": [324, 604, 107, 22]}, {"word": "Nu", "position": [164, 649, 44, 21]}, {"word": "weten", "position": [218, 650, 89, 20]}, {"word": "ze", "position": [317, 655, 30, 15]}, {"word": "het", "position": [359, 649, 46, 21]}, {"word": "nog", "position": [417, 655, 56, 21]}, {"word": "niet.", "position": [483, 649, 64, 21]}, {"word": "Want", "position": [560, 649, 75, 21]}, {"word": "wat", "position": [646, 650, 52, 20]}, {"word": "is", "position": [710, 649, 24, 21]}, {"word": "nou", "position": [164, 699, 56, 16]}, {"word": "waf?", "position": [230, 693, 67, 22]}, {"word": "\u2018Weet", "position": [165, 738, 76, 22]}, {"word": "je", "position": [250, 738, 27, 28]}, {"word": "wat,\u2019", "position": [287, 738, 69, 25]}, {"word": "zegt", "position": [368, 739, 61, 27]}, {"word": "Jip,", "position": [441, 738, 52, 28]}, {"word": "\u2018ik", "position": [506, 738, 35, 21]}, {"word": "loop", "position": [552, 738, 61, 28]}, {"word": "deze", "position": [625, 738, 64, 21]}, {"word": "kant", "position": [164, 783, 66, 22]}, {"word": "uit.", "position": [242, 783, 48, 21]}, {"word": "En", "position": [303, 783, 41, 21]}, {"word": "jij", "position": [352, 783, 29, 28]}, {"word": "moet", "position": [395, 784, 72, 21]}, {"word": "die", "position": [479, 783, 43, 22]}, {"word": "kant", "position": [533, 783, 66, 21]}, {"word": "uit", "position": [611, 783, 40, 21]}, {"word": "lopen,", "position": [662, 783, 89, 28]}, {"word": "Janneke.", "position": [163, 828, 131, 21]}, {"word": "En", "position": [307, 828, 42, 21]}, {"word": "dan", "position": [360, 828, 54, 21]}, {"word": "kijken", "position": [424, 828, 94, 27]}, {"word": "we", "position": [528, 833, 40, 16]}, {"word": "met", "position": [579, 828, 55, 21]}, {"word": "wie", "position": [645, 828, 50, 21]}, {"word": "Takkie", "position": [164, 872, 100, 22]}, {"word": "meeloopt.\u2019", "position": [275, 872, 151, 28]}, {"word": "\u2018Goed,\u2019", "position": [165, 917, 96, 25]}, {"word": "zegt", "position": [273, 918, 61, 26]}, {"word": "Janneke.", "position": [345, 917, 131, 22]}, {"word": "\u2018Maar", "position": [490, 917, 82, 21]}, {"word": "dan", "position": [583, 917, 54, 21]}, {"word": "moet", "position": [648, 918, 73, 20]}, {"word": "je", "position": [729, 917, 28, 27]}, {"word": "hem", "position": [164, 962, 63, 21]}, {"word": "niet", "position": [238, 962, 56, 21]}, {"word": "roepen.\u2019", "position": [306, 961, 117, 28]}, {"word": "Ze", "position": [164, 1006, 33, 22]}, {"word": "lopen", "position": [208, 1006, 81, 28]}, {"word": "elk", "position": [300, 1006, 44, 22]}, {"word": "een", "position": [355, 1012, 51, 16]}, {"word": "andere", "position": [417, 1006, 100, 22]}, {"word": "kant", "position": [528, 1006, 67, 22]}, {"word": "uit.", "position": [607, 1006, 47, 21]}, {"word": "En", "position": [668, 1006, 41, 21]}, {"word": "Takkie?", "position": [834, 381, 115, 22]}, {"word": "Takkie", "position": [834, 426, 100, 21]}, {"word": "blijft", "position": [944, 425, 71, 28]}, {"word": "zitten.", "position": [1027, 426, 92, 21]}, {"word": "Hij", "position": [1132, 426, 42, 27]}, {"word": "kijkt", "position": [1187, 426, 69, 27]}, {"word": "eerst", "position": [1268, 426, 72, 21]}, {"word": "naar", "position": [1352, 431, 67, 16]}, {"word": "Jip", "position": [834, 470, 44, 28]}, {"word": "en", "position": [889, 476, 35, 16]}, {"word": "dan", "position": [935, 470, 54, 22]}, {"word": "weer", "position": [1000, 476, 71, 16]}, {"word": "naar", "position": [1081, 476, 68, 16]}, {"word": "Janneke.", "position": [1159, 470, 130, 22]}, {"word": "Hij", "position": [1302, 470, 42, 28]}, {"word": "kijkt", "position": [1357, 470, 69, 28]}, {"word": "aldoor", "position": [835, 515, 94, 21]}, {"word": "van", "position": [939, 521, 53, 15]}, {"word": "de", "position": [1003, 515, 33, 21]}, {"word": "een", "position": [1047, 521, 51, 15]}, {"word": "naar", "position": [1109, 521, 67, 15]}, {"word": "de", "position": [1187, 515, 33, 21]}, {"word": "ander.", "position": [1231, 515, 89, 21]}, {"word": "Maar", "position": [1332, 515, 77, 21]}, {"word": "hij", "position": [1420, 515, 36, 27]}, {"word": "blijft", "position": [834, 559, 71, 28]}, {"word": "zitten", "position": [916, 560, 85, 21]}, {"word": "en", "position": [1012, 565, 34, 16]}, {"word": "hij", "position": [1058, 560, 35, 27]}, {"word": "jankt", "position": [1104, 560, 79, 27]}, {"word": "een", "position": [1195, 565, 50, 16]}, {"word": "beetje.", "position": [1255, 560, 95, 27]}, {"word": "\u2018Hij", "position": [835, 604, 48, 28]}, {"word": "houdt", "position": [897, 605, 85, 21]}, {"word": "van", "position": [993, 610, 54, 16]}, {"word": "ons", "position": [1058, 610, 50, 16]}, {"word": "allebei", "position": [1120, 604, 95, 22]}, {"word": "evenveel,\u2019", "position": [1226, 604, 143, 26]}, {"word": "zegt", "position": [1381, 605, 61, 27]}, {"word": "Janneke.", "position": [834, 649, 131, 21]}, {"word": "\u2018Zie", "position": [979, 649, 50, 21]}, {"word": "je", "position": [1037, 649, 27, 27]}, {"word": "wel?\u2019", "position": [1074, 648, 72, 22]}, {"word": "En", "position": [1158, 649, 41, 21]}, {"word": "dat", "position": [1210, 649, 46, 21]}, {"word": "is", "position": [1268, 649, 23, 21]}, {"word": "ook", "position": [1302, 649, 54, 21]}, {"word": "zo.", "position": [1366, 655, 38, 15]}, {"word": "Takkie", "position": [834, 694, 100, 21]}, {"word": "is", "position": [946, 694, 23, 21]}, {"word": "een", "position": [980, 699, 51, 16]}, {"word": "heel", "position": [1042, 694, 60, 21]}, {"word": "lief", "position": [1113, 693, 48, 22]}, {"word": "hondje.", "position": [1169, 694, 108, 27]}, {"word": "Maar", "position": [1290, 694, 76, 21]}, {"word": "hij", "position": [1377, 694, 36, 27]}, {"word": "is", "position": [1426, 694, 24, 21]}, {"word": "zo", "position": [834, 744, 32, 15]}, {"word": "bang", "position": [876, 738, 75, 28]}, {"word": "voor", "position": [960, 744, 67, 15]}, {"word": "de", "position": [1038, 738, 33, 21]}, {"word": "poes.", "position": [1081, 744, 74, 22]}, {"word": "Telkens", "position": [1168, 738, 114, 22]}, {"word": "vergeet", "position": [1292, 739, 111, 27]}, {"word": "hij", "position": [1415, 738, 36, 28]}, {"word": "weer", "position": [834, 788, 71, 16]}, {"word": "dat", "position": [916, 783, 46, 21]}, {"word": "er", "position": [973, 788, 30, 16]}, {"word": "ook", "position": [1014, 783, 53, 21]}, {"word": "een", "position": [1078, 788, 51, 16]}, {"word": "poes", "position": [1139, 788, 66, 22]}, {"word": "is.", "position": [1217, 783, 30, 21]}, {"word": "Telkens", "position": [1261, 783, 113, 21]}, {"word": "komt", "position": [1385, 783, 75, 21]}, {"word": "Takkie", "position": [834, 828, 100, 21]}, {"word": "vrolijk", "position": [944, 828, 99, 27]}, {"word": "binnen", "position": [1052, 827, 104, 22]}, {"word": "bij", "position": [1166, 828, 35, 27]}, {"word": "Janneke", "position": [1231, 828, 106, 21]}, {"word": "thuis,", "position": [1348, 828, 84, 25]}, {"word": "om", "position": [835, 878, 44, 16]}, {"word": "uit", "position": [890, 872, 40, 22]}, {"word": "zijn", "position": [941, 872, 54, 28]}, {"word": "bak", "position": [1006, 872, 54, 22]}, {"word": "te", "position": [1070, 873, 27, 21]}, {"word": "eten.", "position": [1108, 873, 70, 21]}, {"word": "En", "position": [1191, 872, 42, 21]}, {"word": "dan", "position": [1243, 872, 55, 22]}, {"word": "hoort", "position": [1309, 872, 79, 22]}, {"word": "hij", "position": [1400, 872, 36, 28]}, {"word": "een", "position": [835, 967, 51, 16]}, {"word": "dikke", "position": [896, 962, 82, 21]}, {"word": "staart.", "position": [989, 962, 94, 21]}, {"word": "En", "position": [1096, 962, 42, 20]}, {"word": "ze", "position": [1148, 967, 30, 16]}, {"word": "blaast", "position": [1188, 962, 88, 21]}, {"word": "heel", "position": [1288, 962, 60, 21]}, {"word": "hard.", "position": [1359, 962, 76, 21]}, {"word": "Zij", "position": [834, 1006, 35, 28]}, {"word": "is", "position": [883, 1006, 23, 21]}, {"word": "heel", "position": [918, 1006, 60, 22]}, {"word": "boos", "position": [988, 1006, 68, 21]}, {"word": "op", "position": [1067, 1012, 34, 22]}, {"word": "Takkie.", "position": [1112, 1006, 107, 22]}, {"word": "Dan", "position": [1232, 1006, 60, 22]}, {"word": "schrikt", "position": [1303, 1006, 105, 22]}]